clusterdc/__init__.py
clusterdc/data/__init__.py
clusterdc/main/__init__.py
clusterdc/main/main.py
clusterdc/plotting/__init__.py
clusterdc/plotting/plotting.py
clusterdc/utils/__init__.py
clusterdc/utils/utils.py
clusterdc-0.2.0.dist-info/LICENSE.txt
clusterdc-0.2.0.dist-info/METADATA
clusterdc-0.2.0.dist-info/WHEEL
clusterdc-0.2.0.dist-info/top_level.txt
clusterdc-0.2.0.dist-info/RECORD
