Metadata-Version: 2.1
Name: clusterdc
Version: 0.2.0
Summary: ClusterDC is a fast and robust density-based clustering algorithm for identifying clusters in two-dimensional embeddings. Initially developed for geochemists, it is applicable across natural sciences and engineering fields, aiding in the analysis of complex datasets by identifying meaningful patterns in data.
Author: Samer Hmoud & Maximilien Meyrieux
Author-email: geo.samer.hmoud@gmail.com
Classifier: Programming Language :: Python :: 3
Classifier: License :: OSI Approved :: MIT License
Classifier: Operating System :: OS Independent
Requires-Python: >=3.6
License-File: LICENSE.txt
Requires-Dist: numpy>=1.22.4
Requires-Dist: pandas>=2.0.3
Requires-Dist: scipy>=1.10.1
Requires-Dist: seaborn>=0.11.2
Requires-Dist: matplotlib>=3.7.1
Requires-Dist: shapely>=2.0.4
Requires-Dist: networkx>=3.1
